D0FUS.py
D0FUS_BIB/D0FUS_import.py
D0FUS_BIB/D0FUS_parameterization.py
D0FUS_BIB/D0FUS_physical_functions.py
D0FUS_BIB/D0FUS_radial_build_functions.py
D0FUS_EXE/D0FUS_genetic.py
D0FUS_EXE/D0FUS_run.py
D0FUS_EXE/D0FUS_scan.py
d0fus-1.0.4.dist-info/licenses/LICENSE
d0fus-1.0.4.dist-info/METADATA
d0fus-1.0.4.dist-info/WHEEL
d0fus-1.0.4.dist-info/entry_points.txt
d0fus-1.0.4.dist-info/top_level.txt
d0fus-1.0.4.dist-info/RECORD
